deep_training/__init__.py
deep_training/data_helper/__init__.py
deep_training/data_helper/ac_args.py
deep_training/data_helper/base_args.py
deep_training/data_helper/cl_args.py
deep_training/data_helper/data_helper.py
deep_training/data_helper/hf_args.py
deep_training/data_helper/mlm_args.py
deep_training/data_helper/pl_agrs.py
deep_training/data_helper/training_args.py
deep_training/nlp/__init__.py
deep_training/nlp/layers/__init__.py
deep_training/nlp/layers/activate.py
deep_training/nlp/layers/crf.py
deep_training/nlp/layers/handshakingkernel.py
deep_training/nlp/layers/mask.py
deep_training/nlp/layers/mhslayer.py
deep_training/nlp/layers/norm.py
deep_training/nlp/layers/ppo.py
deep_training/nlp/layers/prefix_encoder.py
deep_training/nlp/layers/seq_pointer.py
deep_training/nlp/layers/w2ner.py
deep_training/nlp/layers/petl/__init__.py
deep_training/nlp/layers/petl/constants.py
deep_training/nlp/layers/petl/petl_layer.py
deep_training/nlp/layers/petl/utils.py
deep_training/nlp/layers/petl/adalora/__init__.py
deep_training/nlp/layers/petl/adalora/bnb.py
deep_training/nlp/layers/petl/adalora/gptq.py
deep_training/nlp/layers/petl/adalora/layer.py
deep_training/nlp/layers/petl/ia3/__init__.py
deep_training/nlp/layers/petl/ia3/bnb.py
deep_training/nlp/layers/petl/ia3/layer.py
deep_training/nlp/layers/petl/loha/__init__.py
deep_training/nlp/layers/petl/loha/layer.py
deep_training/nlp/layers/petl/lokr/__init__.py
deep_training/nlp/layers/petl/lokr/layer.py
deep_training/nlp/layers/petl/lora/__init__.py
deep_training/nlp/layers/petl/lora/bnb.py
deep_training/nlp/layers/petl/lora/gptq.py
deep_training/nlp/layers/petl/lora/layer.py
deep_training/nlp/layers/petl/lycoris/__init__.py
deep_training/nlp/layers/petl/lycoris/layer.py
deep_training/nlp/layers/petl/prompt/__init__.py
deep_training/nlp/layers/petl/prompt/adaption_prompt.py
deep_training/nlp/layers/petl/prompt/p_tuning.py
deep_training/nlp/layers/petl/prompt/prefix_tuning.py
deep_training-0.3.0.dist-info/METADATA
deep_training-0.3.0.dist-info/WHEEL
deep_training-0.3.0.dist-info/entry_points.txt
deep_training-0.3.0.dist-info/top_level.txt
deep_training-0.3.0.dist-info/RECORD
