Metadata-Version: 2.1
Name: deep-training
Version: 0.3.0
Summary: an easy training architecture
Home-page: https://github.com/ssbuild/deep_training
Author: ssbuild
Author-email: 9727464@qq.com
License: Apache License 2.0
Requires-Dist: lightning <50.0,>=2.0
Requires-Dist: numpy-io <0.1.0,>=0.0.10
Requires-Dist: sentencepiece
Requires-Dist: numpy
Requires-Dist: transformers >=4.39
Requires-Dist: seqmetric
Requires-Dist: scipy
Requires-Dist: scikit-learn
Requires-Dist: tensorboard
Requires-Dist: tqdm
Requires-Dist: six
Requires-Dist: pyyaml
Requires-Dist: safetensors
Requires-Dist: fastdatasets >=0.9.17
